{
  "mailServer": {
    "address": "imap.gmail.com",
    "smtp": {
      "address": "smtp.gmail.com",
      "port": 587
    },
    "user": "sergeeva.dmca@gmail.com",
    "password": "96gNj~Mx8Xar_T!%xb",
    "path": "dmca_abuse",
    "processedPath": "Processed",
    "adminRecipients" : [
      "shalimandr@gmail.com"
    ]
  },
  "openLoad": {
    "address": "https://openload.co/account",
    "user": "sergeeva.dmca@gmail.com",
    "password": "3055710422",
    "API_login": "f69dadb96479d45a",
    "API_Key": "dQ4vhRKm",
    "linkPrefix" : "https://openload.co/f/"
  },
  "wordPress" : {
    "endpoint": "http://stream-tv-series.co/wp-json",
    "user": "Codered",
    "password": "winningthevictory123**",
    "base64token" : "Q29kZXJlZDp3aW5uaW5ndGhldmljdG9yeTEyMyoq"
  },
  "mailFilter": {
    "from": "dmca@openload.co",
    "subject": "Your file(s) on openload got deleted due to a DMCA report",
    "messagesToReadCount": 40
  },
  "refreshDB_interval_sec": 300,
  "checkEmail_interval": 10,

  "installed": {
    "client_id": "809610701255-6lv54ge3q6eq1gdte8ko7n2l1cc58c3r.apps.googleusercontent.com",
    "project_id": "woven-icon-176221",
    "auth_uri": "https://accounts.google.com/o/oauth2/auth",
    "token_uri": "https://accounts.google.com/o/oauth2/token",
    "auth_provider_x509_cert_url": "https://www.googleapis.com/oauth2/v1/certs",
    "client_secret": "ZDH-QkmtZDMSWapSSarIIGLE",
    "redirect_uris": ["urn:ietf:wg:oauth:2.0:oob", "http://localhost"]
  },
  "catalog": {
    "sheetId": "1GyBjpFrhetXLuxibq2vt5PcrBmLPnUqOlLgl_9UuDo8",
    "sheetName": "Catalog",
    "range": "B2:B10000"
  },
  "abuses": {
    "sheetId": "1GyBjpFrhetXLuxibq2vt5PcrBmLPnUqOlLgl_9UuDo8",
    "sheetName": "Abuses",
    "range": "B14:14"
  },
  "postsUpdate" : {
    "sheetId": "1GyBjpFrhetXLuxibq2vt5PcrBmLPnUqOlLgl_9UuDo8",
    "sheetName": "New Post",
    "range": "A2:B115"
  },
  "testSheetId": "1uMwMi6K312STQoBfS3sEkmqdaHdwiVBnPAUp6o_24vE"
}

